pycwgen/__init__.py
pycwgen/__main__.py
pycwgen/cli.py
pycwgen/morse.py
pycwgen/synth.py
pycwgen-0.1.1.dist-info/DESCRIPTION.rst
pycwgen-0.1.1.dist-info/METADATA
pycwgen-0.1.1.dist-info/RECORD
pycwgen-0.1.1.dist-info/WHEEL
pycwgen-0.1.1.dist-info/entry_points.txt
pycwgen-0.1.1.dist-info/metadata.json
pycwgen-0.1.1.dist-info/top_level.txt
