Metadata-Version: 2.0
Name: pycwgen
Version: 0.1.1
Summary: Generate Morse Code (CW) audio files in Python
Home-page: https://github.com/rshk/pycwgen
Author: Samuele Santi
Author-email: samuele@samuelesanti.com
License: BSD License
Platform: UNKNOWN
Classifier: License :: OSI Approved :: BSD License
Classifier: Programming Language :: Python :: 3.6
Requires-Dist: PySoundFile
Requires-Dist: click
Requires-Dist: numpy
